setup.cfg
setup.py
DSDownload.egg-info/PKG-INFO
DSDownload.egg-info/SOURCES.txt
DSDownload.egg-info/dependency_links.txt
DSDownload.egg-info/entry_points.txt
DSDownload.egg-info/not-zip-safe
DSDownload.egg-info/top_level.txt
src/DSDownload.py
src/__init__.py