Metadata-Version: 1.0
Name: DSDownload
Version: 1.6.0.0
Summary: Program and module for download queue optimization using multi-thread.
Home-page: https://github.com/DiSiqueira/DSDownload
Author: Diego Siqueira
Author-email: dieg0@live.com
License: MIT
Keywords: download,thread,speed,resume,multi,simple
Platform: UNKNOWN
